wisp/__init__.py
wisp/util.py
wisp/server/__init__.py
wisp/server/__main__.py
wisp/server/cli.py
wisp/server/connection.py
wisp/server/http.py
wisp/server/net.py
wisp/server/ratelimit.py
wisp_python-0.8.4.dist-info/licenses/LICENSE
wisp_python-0.8.4.dist-info/licenses/LICENSE_third_party.md
wisp_python-0.8.4.dist-info/METADATA
wisp_python-0.8.4.dist-info/WHEEL
wisp_python-0.8.4.dist-info/top_level.txt
wisp_python-0.8.4.dist-info/RECORD
