Metadata-Version: 2.4
Name: wisp-python
Version: 0.8.4
Summary: An implementation of a Wisp proxy server in Python
Author: ading2210
Project-URL: Homepage, https://github.com/MercuryWorkshop/wisp-server-python
Project-URL: Issues, https://github.com/MercuryWorkshop/wisp-server-python/issues
Classifier: Programming Language :: Python :: 3
Classifier: License :: OSI Approved :: GNU Affero General Public License v3
Classifier: Operating System :: OS Independent
Requires-Python: >=3.9
License-File: LICENSE
License-File: LICENSE_third_party.md
Requires-Dist: websockets
Requires-Dist: asyncudp
Requires-Dist: python-socks[asyncio]
Requires-Dist: uvloop; sys_platform != "win32" and sys_platform != "cygwin"
Requires-Dist: winloop; sys_platform == "win32" or sys_platform == "cygwin"
Dynamic: license-file
